setup.py
cascade/__init__.py
cascade/imap_copy.py
cascade/imap_server.py
cascade.egg-info/PKG-INFO
cascade.egg-info/SOURCES.txt
cascade.egg-info/dependency_links.txt
cascade.egg-info/entry_points.txt
cascade.egg-info/requires.txt
cascade.egg-info/top_level.txt
cmd/__init__.py
cmd/app.py